mylog/__init__.py
mylog/py.typed
python_mylog-0.10.0.dist-info/LICENSE
python_mylog-0.10.0.dist-info/METADATA
python_mylog-0.10.0.dist-info/WHEEL
python_mylog-0.10.0.dist-info/top_level.txt
python_mylog-0.10.0.dist-info/RECORD
