Metadata-Version: 2.1
Name: python_mylog
Version: 0.10.0
Summary: My logger library.
Author-email: Koviubi56 <koviubi56@duck.com>
License: GPL-3.0-or-later
Project-URL: Release notes, https://github.com/koviubi56/mylog/blob/main/CHANGELOG.md
Project-URL: Source, https://github.com/koviubi56/mylog
Project-URL: Bug Tracker, https://github.com/koviubi56/mylog/issues
Keywords: logger,log,logging
Classifier: Development Status :: 4 - Beta
Classifier: Intended Audience :: Developers
Classifier: License :: OSI Approved :: GNU General Public License v3 or later (GPLv3+)
Classifier: Natural Language :: English
Classifier: Operating System :: OS Independent
Classifier: Programming Language :: Python
Classifier: Programming Language :: Python :: 3
Classifier: Programming Language :: Python :: 3 :: Only
Classifier: Programming Language :: Python :: 3.10
Classifier: Programming Language :: Python :: 3.11
Classifier: Programming Language :: Python :: 3.12
Classifier: Programming Language :: Python :: 3.13
Classifier: Programming Language :: Python :: Implementation :: CPython
Classifier: Topic :: System :: Logging
Classifier: Typing :: Typed
Requires-Python: >=3.10
License-File: LICENSE
Requires-Dist: termcolor >=0.2
Requires-Dist: typing-extensions
Provides-Extra: dev
Requires-Dist: nox ; extra == 'dev'
Requires-Dist: python-lemming ; extra == 'dev'
